esxi_netinit/__init__.py
esxi_netinit/esxconfig.py
esxi_netinit/esxhost.py
esxi_netinit/link.py
esxi_netinit/main.py
esxi_netinit/meta_data.py
esxi_netinit/metadata.py
esxi_netinit/network.py
esxi_netinit/network_data.py
esxi_netinit/nic.py
esxi_netinit/nic_list.py
esxi_netinit/route.py
esxi_netinit/service.py
esxi_netinit-0.1.3.dist-info/METADATA
esxi_netinit-0.1.3.dist-info/WHEEL
esxi_netinit-0.1.3.dist-info/entry_points.txt
esxi_netinit-0.1.3.dist-info/RECORD
